poseur.py
poseur_compiler-0.3.4.dist-info/LICENSE
poseur_compiler-0.3.4.dist-info/METADATA
poseur_compiler-0.3.4.dist-info/WHEEL
poseur_compiler-0.3.4.dist-info/entry_points.txt
poseur_compiler-0.3.4.dist-info/top_level.txt
poseur_compiler-0.3.4.dist-info/zip-safe
poseur_compiler-0.3.4.dist-info/RECORD
