Metadata-Version: 2.1
Name: poseur-compiler
Version: 0.3.4
Summary: Back-port compiler for Python 3.8 positional-only parameter syntax.
Home-page: https://github.com/JarryShaw/poseur
Author: Jarry Shaw
Author-email: jarryshaw@icloud.com
License: MIT License
Keywords: positional-only parameters,back-port compiler
Platform: UNKNOWN
Classifier: Development Status :: 5 - Production/Stable
Classifier: Intended Audience :: Developers
Classifier: License :: OSI Approved :: MIT License
Classifier: Natural Language :: English
Classifier: Operating System :: OS Independent
Classifier: Programming Language :: Python
Classifier: Programming Language :: Python :: 3.3
Classifier: Programming Language :: Python :: 3.4
Classifier: Programming Language :: Python :: 3.5
Classifier: Programming Language :: Python :: 3.6
Classifier: Programming Language :: Python :: 3.7
Classifier: Programming Language :: Python :: 3.8
Classifier: Programming Language :: Python :: 3 :: Only
Classifier: Topic :: Software Development
Classifier: Topic :: Utilities
Requires-Python: >=3.3
Requires-Dist: parso (~=0.5.0)
Requires-Dist: tbtrim (>=0.2.1)
